{"slug":"carpet-screen-issue-on-thinkpad-x1-carbon-gen-2","title":"Carpet Screen issue on ThinkPad X1 Carbon Gen 2","date":"2014-08-23","year":2014,"month":"08","day":"23","author":"jinli","categories":["lenovo"],"tags":["Lenovo ThinkPad"],"content":"<p>If you are experiencing garbled or messy display, where the pictures are scrambled in a checkerboard manner, and that your laptop no longer responds to keyboard or trackpoint/trackpad input. Then you should call Lenovo Service, and most likely you would need to get your motherboard replaced by Service.</p>\n<p><img src=\"/assets/img/posts/thinkscopes/2014/08/ThinkPad-X1-carbon-scrambled-screen.webp\" alt=\"ThinkPad x1 Carbon Carpet screen issue\" loading=\"lazy\"></p>\n","url":"/blog/2014/08/23/carpet-screen-issue-on-thinkpad-x1-carbon-gen-2"}